videogrep/__init__.py
videogrep/cli.py
videogrep/fcpxml.py
videogrep/model/README
videogrep/model/am/final.mdl
videogrep/model/conf/mfcc.conf
videogrep/model/conf/model.conf
videogrep/model/graph/Gr.fst
videogrep/model/graph/HCLr.fst
videogrep/model/graph/disambig_tid.int
videogrep/model/graph/phones/word_boundary.int
videogrep/model/ivector/final.dubm
videogrep/model/ivector/final.ie
videogrep/model/ivector/final.mat
videogrep/model/ivector/global_cmvn.stats
videogrep/model/ivector/online_cmvn.conf
videogrep/model/ivector/splice.conf
videogrep/sphinx.py
videogrep/srt.py
videogrep/transcribe.py
videogrep/videogrep.py
videogrep/vtt.py
videogrep-2.3.0.dist-info/LICENSE
videogrep-2.3.0.dist-info/METADATA
videogrep-2.3.0.dist-info/WHEEL
videogrep-2.3.0.dist-info/entry_points.txt
videogrep-2.3.0.dist-info/RECORD
