Metadata-Version: 2.1
Name: videogrep
Version: 2.3.0
Summary: Videogrep is a command line tool that searches through dialog in video and audio files and makes supercuts based on what it finds. Like grep but for video.
Home-page: http://antiboredom.github.io/videogrep/
License: Anti-Capitalist
Keywords: video,supercut
Author: Sam Lavigne
Author-email: splavigne@gmail.com
Requires-Python: >=3.8,<4.0
Classifier: License :: Other/Proprietary License
Classifier: Programming Language :: Python :: 3
Classifier: Programming Language :: Python :: 3.8
Classifier: Programming Language :: Python :: 3.9
Classifier: Programming Language :: Python :: 3.10
Classifier: Programming Language :: Python :: 3.11
Classifier: Programming Language :: Python :: 3.12
Classifier: Topic :: Multimedia :: Sound/Audio :: Speech
Classifier: Topic :: Multimedia :: Video
Classifier: Topic :: Text Processing
Classifier: Topic :: Utilities
Provides-Extra: full
Requires-Dist: beautifulsoup4 (>=4.11.1,<5.0.0)
Requires-Dist: moviepy (>=1.0.3,<2.0.0)
Requires-Dist: vosk (==0.3.32) ; extra == "full"
Project-URL: Repository, https://github.com/antiboredom/videogrep
